{
  "metadata": {
    "data_version": "6",
    "match_id": "SG2_96102475",
    "participants": [
      "2kLmKRArA_KRlUE7dcOXKh4dSoJxIGeeGgINACQXAzHpIJMrxMVrRVlsdQknNtOJU8PvVyt_BHMQLw",
      "UP4IaqoIK0np20AogE3FpMLBXzDeeZwS0vlPcZmQKej6Rlj06OTn2UV2zT3-kacFILSu4Q1rDYKbFA",
      "OVwxwP62jIGunYMocjVGspH8lcI7RT0yv3qyqhP5ynPAHG7ekmNjh4Rv0FJugrLkAVABeSfIMimJhQ",
      "2sCVZCo77dZf116GPaV0J7LFrlC0T4GM0yiSPqOSurjls0AO0Kv7PnISTTG27pgk4aUw1VeKk3ae4w",
      "8eZJcc5IKTNKhWcwzvr18njZ1kpeT1Ae5W4soXQ_5TY5ZvWz7flcFgMte0mQMh9ULDrTK8VLLRd5Yw",
      "zNRMma4XTfvDgdWsHKalLnWJkoXlV-3KudSQ78ZDlAc0UZELJrbjTQrY5I3gVo1O5iflCHVxG17cdQ",
      "n74HHr1ZVukiFLUWQvsNIq-iR1DG_ymeZvCVJXHHi7CEgAJk8R1-Dq0-GzB--e9FaNpRAT9zKCO8aw",
      "8DtM5TFxf8Th9f5SMyh1JAsZ8cIYxIq_d9wKCX7KLxDZwYmfzrKTvukYkk2AEIeslDJAnrajt5ENKQ"
    ]
  },
  "info": {
    "endOfGameResult": "GameComplete",
    "gameCreation": 1757437696000,
    "gameId": 96102475,
    "game_datetime": 1757439970250,
    "game_length": 2224.42431640625,
    "game_version": "Linux Version 15.17.708.5788 (Aug 29 2025/12:30:43) [PUBLIC] <Releases/15.17>",
    "mapId": 22,
    "participants": [
      {
        "companion": {
          "content_ID": "7704c9a7-d9d1-4059-a638-192a2b782aff",
          "item_ID": 77003,
          "skin_ID": 3,
          "species": "PetChibiMorgana"
        },
        "gold_left": 8,
        "last_round": 35,
        "level": 10,
        "missions": {
          "PlayerScore2": 205
        },
        "placement": 3,
        "players_eliminated": 0,
        "puuid": "2kLmKRArA_KRlUE7dcOXKh4dSoJxIGeeGgINACQXAzHpIJMrxMVrRVlsdQknNtOJU8PvVyt_BHMQLw",
        "riotIdGameName": "XenoxMania",
        "riotIdTagline": "SG2",
        "time_eliminated": 2052.87060546875,
        "total_damage_to_players": 119,
        "traits": [
          {
            "name": "TFT15_Bastion",
            "num_units": 1,
            "style": 0,
            "tier_current": 0,
            "tier_total": 3
          },
          {
            "name": "TFT15_Destroyer",
            "num_units": 4,
            "style": 2,
            "tier_current": 3,
            "tier_total": 4
          },
          {
            "name": "TFT15_DragonFist",
            "num_units": 1,
            "style": 3,
            "tier_current": 1,
            "tier_total": 1
          },
          {
            "name": "TFT15_Duelist",
            "num_units": 1,
            "style": 0,
            "tier_current": 0,
            "tier_total": 3
          },
          {
            "name": "TFT15_Edgelord",
            "num_units": 1,
            "style": 0,
            "tier_current": 0,
            "tier_total": 3
          },
          {
            "name": "TFT15_ElTigre",
            "num_units": 1,
            "style": 3,
            "tier_current": 1,
            "tier_total": 1
          },
          {
            "name": "TFT15_Heavyweight",
            "num_units": 2,
            "style": 1,
            "tier_current": 1,
            "tier_total": 3
          },
          {
            "name": "TFT15_Juggernaut",
            "num_units": 2,
            "style": 1,
            "tier_current": 1,
            "tier_total": 3
          },
          {
            "name": "TFT15_Luchador",
            "num_units": 1,
            "style": 0,
            "tier_current": 0,
            "tier_total": 2
          },
          {
            "name": "TFT15_OldMentor",
            "num_units": 4,
            "style": 4,
            "tier_current": 3,
            "tier_total": 3
          },
          {
            "name": "TFT15_SentaiRanger",
            "num_units": 3,
            "style": 1,
            "tier_current": 1,
            "tier_total": 4
          },
          {
            "name": "TFT15_Strategist",
            "num_units": 2,
            "style": 1,
            "tier_current": 1,
            "tier_total": 4
          },
          {
            "name": "TFT15_SupremeCells",
            "num_units": 1,
            "style": 0,
            "tier_current": 0,
            "tier_total": 3
          }
        ],
        "units": [
          {
            "character_id": "TFT15_Aatrox",
            "itemNames": [],
            "name": "",
            "rarity": 0,
            "tier": 2
          },
          {
            "character_id": "TFT15_Kobuko",
            "itemNames": [],
            "name": "",
            "rarity": 1,
            "tier": 2
          },
          {
            "character_id": "TFT15_Udyr",
            "itemNames": [
              "TFT_Item_WarmogsArmor",
              "TFT_Item_GargoyleStoneplate",
              "TFT_Item_IonicSpark"
            ],
            "name": "",
            "rarity": 2,
            "tier": 2
          },
          {
            "character_id": "TFT15_Yasuo",
            "itemNames": [
              "TFT_Item_ThiefsGloves",
              "TFT_Item_RunaansHurricane",
              "TFT_Item_UnstableConcoction"
            ],
            "name": "",
            "rarity": 2,
            "tier": 2
          },
          {
            "character_id": "TFT15_Senna",
            "itemNames": [],
            "name": "",
            "rarity": 2,
            "tier": 2
          },
          {
            "character_id": "TFT15_Akali",
            "itemNames": [],
            "name": "",
            "rarity": 4,
            "tier": 2
          },
          {
            "character_id": "TFT15_Ryze",
            "itemNames": [
              "TFT_Item_ArchangelsStaff",
              "TFT_Item_PowerGauntlet",
              "TFT_Item_JeweledGauntlet"
            ],
            "name": "",
            "rarity": 4,
            "tier": 2
          },
          {
            "character_id": "TFT15_JarvanIV",
            "itemNames": [],
            "name": "",
            "rarity": 4,
            "tier": 2
          },
          {
            "character_id": "TFT15_Braum",
            "itemNames": [],
            "name": "",
            "rarity": 6,
            "tier": 2
          },
          {
            "character_id": "tft15_leesin",
            "itemNames": [
              "TFT_Item_Bloodthirster",
              "TFT_Item_GuardianAngel",
              "TFT_Item_TitansResolve"
            ],
            "name": "",
            "rarity": 6,
            "tier": 2
          },
          {
            "character_id": "TFT15_Galio",
            "itemNames": [
              "TFT15_RoboRanger_Core"
            ],
            "name": "",
            "rarity": 9,
            "tier": 1
          }
        ],
        "win": true
      },
      {
        "companion": {
          "content_ID": "fcea42c8-c430-433d-8f55-f18394c2a964",
          "item_ID": 66001,
          "skin_ID": 1,
          "species": "PetPoro"
        },
        "gold_left": 19,
        "last_round": 31,
        "level": 7,
        "missions": {
          "PlayerScore2": 90
        },
        "placement": 6,
        "players_eliminated": 0,
        "puuid": "UP4IaqoIK0np20AogE3FpMLBXzDeeZwS0vlPcZmQKej6Rlj06OTn2UV2zT3-kacFILSu4Q1rDYKbFA",
        "riotIdGameName": "Yujung2",
        "riotIdTagline": "Song",
        "time_eliminated": 1803.5968017578125,
        "total_damage_to_players": 78,
        "traits": [
          {
            "name": "TFT15_Destroyer",
            "num_units": 2,
            "style": 1,
            "tier_current": 1,
            "tier_total": 4
          },
          {
            "name": "TFT15_Duelist",
            "num_units": 2,
            "style": 1,
            "tier_current": 1,
            "tier_total": 3
          },
          {
            "name": "TFT15_Heavyweight",
            "num_units": 2,
            "style": 1,
            "tier_current": 1,
            "tier_total": 3
          },
          {
            "name": "TFT15_Juggernaut",
            "num_units": 2,
            "style": 1,
            "tier_current": 1,
            "tier_total": 3
          },
          {
            "name": "TFT15_MonsterTrainer",
            "num_units": 1,
            "style": 3,
            "tier_current": 1,
            "tier_total": 1
          },
          {
            "name": "TFT15_OldMentor",
            "num_units": 1,
            "style": 1,
            "tier_current": 1,
            "tier_total": 3
          },
          {
            "name": "TFT15_Protector",
            "num_units": 1,
            "style": 0,
            "tier_current": 0,
            "tier_total": 3
          },
          {
            "name": "TFT15_SentaiRanger",
            "num_units": 1,
            "style": 0,
            "tier_current": 0,
            "tier_total": 4
          },
          {
            "name": "TFT15_Spellslinger",
            "num_units": 1,
            "style": 0,
            "tier_current": 0,
            "tier_total": 3
          },
          {
            "name": "TFT15_SupremeCells",
            "num_units": 4,
            "style": 4,
            "tier_current": 3,
            "tier_total": 3
          }
        ],
        "units": [
          {
            "character_id": "TFT15_Kennen",
            "itemNames": [],
            "name": "",
            "rarity": 0,
            "tier": 2
          },
          {
            "character_id": "TFT15_Aatrox",
            "itemNames": [],
            "name": "",
            "rarity": 0,
            "tier": 2
          },
          {
            "character_id": "TFT15_KaiSa",
            "itemNames": [
              "TFT_Item_PowerGauntlet",
              "TFT_Item_GuinsoosRageblade",
              "TFT_Item_InfinityEdge"
            ],
            "name": "",
            "rarity": 1,
            "tier": 3
          },
          {
            "character_id": "TFT15_Darius",
            "itemNames": [
              "TFT15_Item_DestroyerEmblemItem",
              "TFT_Item_Bloodthirster",
              "TFT_Item_LastWhisper"
            ],
            "name": "",
            "rarity": 2,
            "tier": 3
          },
          {
            "character_id": "tft15_rammus",
            "itemNames": [
              "TFT_Item_Crownguard",
              "TFT_Item_GargoyleStoneplate",
              "TFT_Item_Redemption"
            ],
            "name": "",
            "rarity": 2,
            "tier": 3
          },
          {
            "character_id": "TFT15_Udyr",
            "itemNames": [],
            "name": "",
            "rarity": 2,
            "tier": 2
          },
          {
            "character_id": "TFT15_Akali",
            "itemNames": [
              "TFT_Item_UnstableConcoction",
              "TFT_Item_MadredsBloodrazor"
            ],
            "name": "",
            "rarity": 4,
            "tier": 1
          }
        ],
        "win": false
      },
      {
        "companion": {
          "content_ID": "ecbbc3d8-c9ea-4894-8d1a-bccdfb327105",
          "item_ID": 34001,
          "skin_ID": 1,
          "species": "PetChibiEkko"
        },
        "gold_left": 0,
        "last_round": 38,
        "level": 9,
        "missions": {
          "PlayerScore2": 221
        },
        "placement": 2,
        "players_eliminated": 2,
        "puuid": "OVwxwP62jIGunYMocjVGspH8lcI7RT0yv3qyqhP5ynPAHG7ekmNjh4Rv0FJugrLkAVABeSfIMimJhQ",
        "riotIdGameName": "wifi slow brain",
        "riotIdTagline": "slowr",
        "time_eliminated": 2209.002685546875,
        "total_damage_to_players": 166,
        "traits": [
          {
            "name": "TFT15_BattleAcademia",
            "num_units": 1,
            "style": 0,
            "tier_current": 0,
            "tier_total": 4
          },
          {
            "name": "TFT15_Edgelord",
            "num_units": 2,
            "style": 1,
            "tier_current": 1,
            "tier_total": 3
          },
          {
            "name": "TFT15_Empyrean",
            "num_units": 1,
            "style": 0,
            "tier_current": 0,
            "tier_total": 3
          },
          {
            "name": "TFT15_GemForce",
            "num_units": 2,
            "style": 0,
            "tier_current": 0,
            "tier_total": 4
          },
          {
            "name": "TFT15_OldMentor",
            "num_units": 1,
            "style": 1,
            "tier_current": 1,
            "tier_total": 3
          },
          {
            "name": "TFT15_Protector",
            "num_units": 4,
            "style": 2,
            "tier_current": 2,
            "tier_total": 3
          },
          {
            "name": "TFT15_Rosemother",
            "num_units": 1,
            "style": 3,
            "tier_current": 1,
            "tier_total": 1
          },
          {
            "name": "TFT15_SentaiRanger",
            "num_units": 1,
            "style": 0,
            "tier_current": 0,
            "tier_total": 4
          },
          {
            "name": "TFT15_Sniper",
            "num_units": 1,
            "style": 0,
            "tier_current": 0,
            "tier_total": 4
          },
          {
            "name": "TFT15_StarGuardian",
            "num_units": 3,
            "style": 2,
            "tier_current": 2,
            "tier_total": 12
          },
          {
            "name": "TFT15_Strategist",
            "num_units": 2,
            "style": 1,
            "tier_current": 1,
            "tier_total": 4
          }
        ],
        "units": [
          {
            "character_id": "TFT15_Rakan",
            "itemNames": [
              "TFT_Item_SteraksGage",
              "TFT_Item_TitansResolve",
              "TFT_Item_ArchangelsStaff"
            ],
            "name": "",
            "rarity": 1,
            "tier": 3
          },
          {
            "character_id": "TFT15_Xayah",
            "itemNames": [
              "TFT5_Item_RunaansHurricaneRadiant",
              "TFT_Item_GuinsoosRageblade",
              "TFT_Item_GuinsoosRageblade"
            ],
            "name": "",
            "rarity": 1,
            "tier": 3
          },
          {
            "character_id": "TFT15_Janna",
            "itemNames": [
              "TFT_Item_AdaptiveHelm",
              "TFT_Item_SpearOfShojin",
              "TFT_Item_RapidFireCannon"
            ],
            "name": "",
            "rarity": 1,
            "tier": 3
          },
          {
            "character_id": "TFT15_Yasuo",
            "itemNames": [],
            "name": "",
            "rarity": 2,
            "tier": 2
          },
          {
            "character_id": "TFT15_Neeko",
            "itemNames": [],
            "name": "",
            "rarity": 2,
            "tier": 2
          },
          {
            "character_id": "TFT15_Jinx",
            "itemNames": [],
            "name": "",
            "rarity": 4,
            "tier": 1
          },
          {
            "character_id": "TFT15_KSante",
            "itemNames": [
              "TFT_Item_FrozenHeart",
              "TFT_Item_SpectralGauntlet",
              "TFT_Item_BrambleVest"
            ],
            "name": "",
            "rarity": 4,
            "tier": 2
          },
          {
            "character_id": "TFT15_JarvanIV",
            "itemNames": [],
            "name": "",
            "rarity": 4,
            "tier": 1
          },
          {
            "character_id": "TFT15_Zyra",
            "itemNames": [],
            "name": "",
            "rarity": 6,
            "tier": 1
          }
        ],
        "win": true
      },
      {
        "companion": {
          "content_ID": "8c83d917-84b2-4e02-9734-31ae91f5069e",
          "item_ID": 63003,
          "skin_ID": 3,
          "species": "PetShark"
        },
        "gold_left": 7,
        "last_round": 38,
        "level": 9,
        "missions": {
          "PlayerScore2": 221
        },
        "placement": 1,
        "players_eliminated": 4,
        "puuid": "2sCVZCo77dZf116GPaV0J7LFrlC0T4GM0yiSPqOSurjls0AO0Kv7PnISTTG27pgk4aUw1VeKk3ae4w",
        "riotIdGameName": "PK Angsana",
        "riotIdTagline": "TREE",
        "time_eliminated": 2211.256103515625,
        "total_damage_to_players": 107,
        "traits": [
          {
            "name": "TFT15_Destroyer",
            "num_units": 5,
            "style": 4,
            "tier_current": 4,
            "tier_total": 4
          },
          {
            "name": "TFT15_DragonFist",
            "num_units": 1,
            "style": 3,
            "tier_current": 1,
            "tier_total": 1
          },
          {
            "name": "TFT15_Duelist",
            "num_units": 1,
            "style": 0,
            "tier_current": 0,
            "tier_total": 3
          },
          {
            "name": "TFT15_Edgelord",
            "num_units": 1,
            "style": 0,
            "tier_current": 0,
            "tier_total": 3
          },
          {
            "name": "TFT15_Heavyweight",
            "num_units": 3,
            "style": 1,
            "tier_current": 1,
            "tier_total": 3
          },
          {
            "name": "TFT15_Juggernaut",
            "num_units": 2,
            "style": 1,
            "tier_current": 1,
            "tier_total": 3
          },
          {
            "name": "TFT15_Luchador",
            "num_units": 1,
            "style": 0,
            "tier_current": 0,
            "tier_total": 2
          },
          {
            "name": "TFT15_OldMentor",
            "num_units": 4,
            "style": 4,
            "tier_current": 3,
            "tier_total": 3
          },
          {
            "name": "TFT15_Prodigy",
            "num_units": 1,
            "style": 0,
            "tier_current": 0,
            "tier_total": 4
          },
          {
            "name": "TFT15_SentaiRanger",
            "num_units": 3,
            "style": 1,
            "tier_current": 1,
            "tier_total": 4
          },
          {
            "name": "TFT15_Strategist",
            "num_units": 2,
            "style": 1,
            "tier_current": 1,
            "tier_total": 4
          },
          {
            "name": "TFT15_SupremeCells",
            "num_units": 3,
            "style": 2,
            "tier_current": 2,
            "tier_total": 3
          }
        ],
        "units": [
          {
            "character_id": "TFT15_Aatrox",
            "itemNames": [],
            "name": "",
            "rarity": 0,
            "tier": 2
          },
          {
            "character_id": "TFT15_Kobuko",
            "itemNames": [
              "TFT_Item_DragonsClaw",
              "TFT_Item_WarmogsArmor",
              "TFT_Item_FrozenHeart"
            ],
            "name": "",
            "rarity": 1,
            "tier": 2
          },
          {
            "character_id": "TFT15_Udyr",
            "itemNames": [
              "TFT15_Item_RingKingsEmblemItem",
              "TFT15_Item_HeavyweightEmblemItem"
            ],
            "name": "",
            "rarity": 2,
            "tier": 2
          },
          {
            "character_id": "TFT15_Yasuo",
            "itemNames": [
              "TFT15_Item_DestroyerEmblemItem"
            ],
            "name": "",
            "rarity": 2,
            "tier": 2
          },
          {
            "character_id": "TFT15_Senna",
            "itemNames": [
              "TFT15_Item_SupremeCellsEmblemItem"
            ],
            "name": "",
            "rarity": 2,
            "tier": 2
          },
          {
            "character_id": "TFT15_Akali",
            "itemNames": [],
            "name": "",
            "rarity": 4,
            "tier": 2
          },
          {
            "character_id": "TFT15_Ryze",
            "itemNames": [
              "TFT_Item_PowerGauntlet",
              "TFT_Item_ArchangelsStaff",
              "TFT_Item_HextechGunblade"
            ],
            "name": "",
            "rarity": 4,
            "tier": 2
          },
          {
            "character_id": "TFT15_JarvanIV",
            "itemNames": [
              "TFT15_Item_ProdigyEmblemItem",
              "TFT_Item_Redemption"
            ],
            "name": "",
            "rarity": 4,
            "tier": 2
          },
          {
            "character_id": "tft15_leesin",
            "itemNames": [
              "TFT_Item_PowerGauntlet",
              "TFT_Item_InfinityEdge",
              "TFT15_Item_SupremeCellsEmblemItem"
            ],
            "name": "",
            "rarity": 6,
            "tier": 2
          },
          {
            "character_id": "TFT15_Galio",
            "itemNames": [
              "TFT15_RoboRanger_Core"
            ],
            "name": "",
            "rarity": 9,
            "tier": 1
          }
        ],
        "win": true
      },
      {
        "companion": {
          "content_ID": "1aa982cd-7fcc-4bab-be7b-9e38ddcd9c93",
          "item_ID": 52015,
          "skin_ID": 15,
          "species": "PetBunny"
        },
        "gold_left": 0,
        "last_round": 31,
        "level": 9,
        "missions": {
          "PlayerScore2": 90
        },
        "placement": 5,
        "players_eliminated": 0,
        "puuid": "8eZJcc5IKTNKhWcwzvr18njZ1kpeT1Ae5W4soXQ_5TY5ZvWz7flcFgMte0mQMh9ULDrTK8VLLRd5Yw",
        "riotIdGameName": "pochacco",
        "riotIdTagline": "riel",
        "time_eliminated": 1810.0054931640625,
        "total_damage_to_players": 83,
        "traits": [
          {
            "name": "TFT15_Bastion",
            "num_units": 1,
            "style": 0,
            "tier_current": 0,
            "tier_total": 3
          },
          {
            "name": "TFT15_Edgelord",
            "num_units": 1,
            "style": 0,
            "tier_current": 0,
            "tier_total": 3
          },
          {
            "name": "TFT15_GemForce",
            "num_units": 1,
            "style": 0,
            "tier_current": 0,
            "tier_total": 4
          },
          {
            "name": "TFT15_Heavyweight",
            "num_units": 2,
            "style": 1,
            "tier_current": 1,
            "tier_total": 3
          },
          {
            "name": "TFT15_OldMentor",
            "num_units": 1,
            "style": 1,
            "tier_current": 1,
            "tier_total": 3
          },
          {
            "name": "TFT15_Prodigy",
            "num_units": 2,
            "style": 1,
            "tier_current": 1,
            "tier_total": 4
          },
          {
            "name": "TFT15_Protector",
            "num_units": 1,
            "style": 0,
            "tier_current": 0,
            "tier_total": 3
          },
          {
            "name": "TFT15_Sniper",
            "num_units": 1,
            "style": 0,
            "tier_current": 0,
            "tier_total": 4
          },
          {
            "name": "TFT15_Spellslinger",
            "num_units": 1,
            "style": 0,
            "tier_current": 0,
            "tier_total": 3
          },
          {
            "name": "TFT15_StarGuardian",
            "num_units": 8,
            "style": 4,
            "tier_current": 7,
            "tier_total": 12
          }
        ],
        "units": [
          {
            "character_id": "TFT15_Rell",
            "itemNames": [
              "TFT_Item_ChainVest"
            ],
            "name": "",
            "rarity": 0,
            "tier": 2
          },
          {
            "character_id": "TFT15_Syndra",
            "itemNames": [],
            "name": "",
            "rarity": 0,
            "tier": 2
          },
          {
            "character_id": "TFT15_Kobuko",
            "itemNames": [],
            "name": "",
            "rarity": 1,
            "tier": 1
          },
          {
            "character_id": "TFT15_Xayah",
            "itemNames": [],
            "name": "",
            "rarity": 1,
            "tier": 1
          },
          {
            "character_id": "TFT15_Ahri",
            "itemNames": [
              "TFT_Item_GuinsoosRageblade"
            ],
            "name": "",
            "rarity": 2,
            "tier": 2
          },
          {
            "character_id": "TFT15_Neeko",
            "itemNames": [],
            "name": "",
            "rarity": 2,
            "tier": 2
          },
          {
            "character_id": "TFT15_Jinx",
            "itemNames": [
              "TFT_Item_GuinsoosRageblade",
              "TFT_Item_Deathblade",
              "TFT_Item_PowerGauntlet"
            ],
            "name": "",
            "rarity": 4,
            "tier": 2
          },
          {
            "character_id": "TFT15_Poppy",
            "itemNames": [
              "TFT_Item_SpectralGauntlet",
              "TFT_Item_NightHarvester",
              "TFT_Item_BrambleVest"
            ],
            "name": "",
            "rarity": 4,
            "tier": 2
          },
          {
            "character_id": "TFT15_Seraphine",
            "itemNames": [
              "TFT_Item_SpearOfShojin",
              "TFT5_Item_StatikkShivRadiant",
              "TFT_Item_AdaptiveHelm"
            ],
            "name": "",
            "rarity": 6,
            "tier": 1
          }
        ],
        "win": false
      },
      {
        "companion": {
          "content_ID": "5601b81d-dfe2-40d7-81c5-4795ac9f6f3f",
          "item_ID": 91002,
          "skin_ID": 2,
          "species": "PetChibiOrianna"
        },
        "gold_left": 0,
        "last_round": 33,
        "level": 9,
        "missions": {
          "PlayerScore2": 191
        },
        "placement": 4,
        "players_eliminated": 1,
        "puuid": "zNRMma4XTfvDgdWsHKalLnWJkoXlV-3KudSQ78ZDlAc0UZELJrbjTQrY5I3gVo1O5iflCHVxG17cdQ",
        "riotIdGameName": "EheEhe",
        "riotIdTagline": "hehe",
        "time_eliminated": 1909.26171875,
        "total_damage_to_players": 90,
        "traits": [
          {
            "name": "TFT15_Bastion",
            "num_units": 2,
            "style": 1,
            "tier_current": 1,
            "tier_total": 3
          },
          {
            "name": "TFT15_Edgelord",
            "num_units": 6,
            "style": 4,
            "tier_current": 3,
            "tier_total": 3
          },
          {
            "name": "TFT15_ElTigre",
            "num_units": 1,
            "style": 3,
            "tier_current": 1,
            "tier_total": 1
          },
          {
            "name": "TFT15_Juggernaut",
            "num_units": 2,
            "style": 1,
            "tier_current": 1,
            "tier_total": 3
          },
          {
            "name": "TFT15_Luchador",
            "num_units": 4,
            "style": 4,
            "tier_current": 2,
            "tier_total": 2
          },
          {
            "name": "TFT15_OldMentor",
            "num_units": 1,
            "style": 1,
            "tier_current": 1,
            "tier_total": 3
          },
          {
            "name": "TFT15_SentaiRanger",
            "num_units": 1,
            "style": 0,
            "tier_current": 0,
            "tier_total": 4
          },
          {
            "name": "TFT15_Sniper",
            "num_units": 1,
            "style": 0,
            "tier_current": 0,
            "tier_total": 4
          },
          {
            "name": "TFT15_SoulFighter",
            "num_units": 2,
            "style": 1,
            "tier_current": 1,
            "tier_total": 5
          },
          {
            "name": "TFT15_TheCrew",
            "num_units": 1,
            "style": 0,
            "tier_current": 0,
            "tier_total": 7
          }
        ],
        "units": [
          {
            "character_id": "TFT15_Gnar",
            "itemNames": [
              "TFT_Item_TearOfTheGoddess"
            ],
            "name": "",
            "rarity": 0,
            "tier": 1
          },
          {
            "character_id": "TFT15_DrMundo",
            "itemNames": [],
            "name": "",
            "rarity": 1,
            "tier": 2
          },
          {
            "character_id": "TFT15_Shen",
            "itemNames": [],
            "name": "",
            "rarity": 1,
            "tier": 1
          },
          {
            "character_id": "TFT15_Yasuo",
            "itemNames": [],
            "name": "",
            "rarity": 2,
            "tier": 2
          },
          {
            "character_id": "TFT15_Samira",
            "itemNames": [
              "TFT_Item_RapidFireCannon",
              "TFT_Item_SpearOfShojin",
              "TFT_Item_InfinityEdge"
            ],
            "name": "",
            "rarity": 4,
            "tier": 2
          },
          {
            "character_id": "TFT15_Sett",
            "itemNames": [
              "TFT_Item_SpectralGauntlet"
            ],
            "name": "",
            "rarity": 4,
            "tier": 2
          },
          {
            "character_id": "TFT15_Volibear",
            "itemNames": [
              "TFT_Item_InfinityEdge",
              "TFT_Item_RunaansHurricane",
              "TFT_Item_PowerGauntlet"
            ],
            "name": "",
            "rarity": 4,
            "tier": 2
          },
          {
            "character_id": "TFT15_Braum",
            "itemNames": [
              "TFT15_Item_EdgelordEmblemItem"
            ],
            "name": "",
            "rarity": 6,
            "tier": 1
          },
          {
            "character_id": "TFT15_Yone",
            "itemNames": [
              "TFT_Item_RunaansHurricane",
              "TFT_Item_TitansResolve"
            ],
            "name": "",
            "rarity": 6,
            "tier": 2
          }
        ],
        "win": true
      },
      {
        "companion": {
          "content_ID": "b83f7c15-188a-43b3-bda3-aaa6d5ce90f0",
          "item_ID": 83002,
          "skin_ID": 2,
          "species": "PetChibiTristana"
        },
        "gold_left": 5,
        "last_round": 27,
        "level": 9,
        "missions": {
          "PlayerScore2": 79
        },
        "placement": 7,
        "players_eliminated": 0,
        "puuid": "n74HHr1ZVukiFLUWQvsNIq-iR1DG_ymeZvCVJXHHi7CEgAJk8R1-Dq0-GzB--e9FaNpRAT9zKCO8aw",
        "riotIdGameName": "indysc2",
        "riotIdTagline": "7777",
        "time_eliminated": 1578.57763671875,
        "total_damage_to_players": 54,
        "traits": [
          {
            "name": "TFT15_Bastion",
            "num_units": 2,
            "style": 1,
            "tier_current": 1,
            "tier_total": 3
          },
          {
            "name": "TFT15_Captain",
            "num_units": 1,
            "style": 3,
            "tier_current": 1,
            "tier_total": 1
          },
          {
            "name": "TFT15_ElTigre",
            "num_units": 1,
            "style": 3,
            "tier_current": 1,
            "tier_total": 1
          },
          {
            "name": "TFT15_Empyrean",
            "num_units": 2,
            "style": 1,
            "tier_current": 1,
            "tier_total": 3
          },
          {
            "name": "TFT15_GemForce",
            "num_units": 3,
            "style": 1,
            "tier_current": 1,
            "tier_total": 4
          },
          {
            "name": "TFT15_Luchador",
            "num_units": 2,
            "style": 1,
            "tier_current": 1,
            "tier_total": 2
          },
          {
            "name": "TFT15_Protector",
            "num_units": 2,
            "style": 1,
            "tier_current": 1,
            "tier_total": 3
          },
          {
            "name": "TFT15_Rosemother",
            "num_units": 1,
            "style": 3,
            "tier_current": 1,
            "tier_total": 1
          },
          {
            "name": "TFT15_SentaiRanger",
            "num_units": 1,
            "style": 0,
            "tier_current": 0,
            "tier_total": 4
          },
          {
            "name": "TFT15_Sniper",
            "num_units": 2,
            "style": 1,
            "tier_current": 1,
            "tier_total": 4
          },
          {
            "name": "TFT15_Spellslinger",
            "num_units": 1,
            "style": 0,
            "tier_current": 0,
            "tier_total": 3
          },
          {
            "name": "TFT15_Strategist",
            "num_units": 2,
            "style": 1,
            "tier_current": 1,
            "tier_total": 4
          },
          {
            "name": "TFT15_TheCrew",
            "num_units": 1,
            "style": 0,
            "tier_current": 0,
            "tier_total": 7
          }
        ],
        "units": [
          {
            "character_id": "TFT15_Gnar",
            "itemNames": [
              "TFT_Item_RunaansHurricane"
            ],
            "name": "",
            "rarity": 0,
            "tier": 2
          },
          {
            "character_id": "TFT15_Janna",
            "itemNames": [],
            "name": "",
            "rarity": 1,
            "tier": 2
          },
          {
            "character_id": "TFT15_Swain",
            "itemNames": [],
            "name": "",
            "rarity": 2,
            "tier": 2
          },
          {
            "character_id": "TFT15_KSante",
            "itemNames": [
              "TFT_Item_GargoyleStoneplate",
              "TFT_Item_BrambleVest",
              "TFT_Item_Redemption"
            ],
            "name": "",
            "rarity": 4,
            "tier": 2
          },
          {
            "character_id": "TFT15_JarvanIV",
            "itemNames": [
              "TFT_Item_ThiefsGloves",
              "TFT_Item_GuardianAngel",
              "TFT_Item_TitansResolve"
            ],
            "name": "",
            "rarity": 4,
            "tier": 2
          },
          {
            "character_id": "TFT15_Braum",
            "itemNames": [],
            "name": "",
            "rarity": 6,
            "tier": 1
          },
          {
            "character_id": "TFT15_Varus",
            "itemNames": [],
            "name": "",
            "rarity": 6,
            "tier": 1
          },
          {
            "character_id": "TFT15_TwistedFate",
            "itemNames": [
              "TFT_Item_GuinsoosRageblade",
              "TFT_Item_BlueBuff",
              "TFT_Item_Deathblade"
            ],
            "name": "",
            "rarity": 6,
            "tier": 2
          },
          {
            "character_id": "TFT15_Zyra",
            "itemNames": [],
            "name": "",
            "rarity": 6,
            "tier": 1
          },
          {
            "character_id": "TFT15_TwistedFate",
            "itemNames": [
              "TFT_Item_GuinsoosRageblade",
              "TFT_Item_BlueBuff",
              "TFT_Item_Deathblade"
            ],
            "name": "",
            "rarity": 6,
            "tier": 2
          }
        ],
        "win": false
      },
      {
        "companion": {
          "content_ID": "ba6b06ee-7d6b-41fd-8757-b42a40dc1811",
          "item_ID": 26007,
          "skin_ID": 7,
          "species": "PetUmbra"
        },
        "gold_left": 32,
        "last_round": 26,
        "level": 7,
        "missions": {
          "PlayerScore2": 75
        },
        "placement": 8,
        "players_eliminated": 0,
        "puuid": "8DtM5TFxf8Th9f5SMyh1JAsZ8cIYxIq_d9wKCX7KLxDZwYmfzrKTvukYkk2AEIeslDJAnrajt5ENKQ",
        "riotIdGameName": "cjwei98",
        "riotIdTagline": "cjw98",
        "time_eliminated": 1519.4393310546875,
        "total_damage_to_players": 36,
        "traits": [
          {
            "name": "TFT15_BattleAcademia",
            "num_units": 1,
            "style": 0,
            "tier_current": 0,
            "tier_total": 4
          },
          {
            "name": "TFT15_Empyrean",
            "num_units": 2,
            "style": 1,
            "tier_current": 1,
            "tier_total": 3
          },
          {
            "name": "TFT15_Luchador",
            "num_units": 1,
            "style": 0,
            "tier_current": 0,
            "tier_total": 2
          },
          {
            "name": "TFT15_Protector",
            "num_units": 5,
            "style": 2,
            "tier_current": 2,
            "tier_total": 3
          },
          {
            "name": "TFT15_Sniper",
            "num_units": 4,
            "style": 2,
            "tier_current": 3,
            "tier_total": 4
          },
          {
            "name": "TFT15_Spellslinger",
            "num_units": 1,
            "style": 0,
            "tier_current": 0,
            "tier_total": 3
          },
          {
            "name": "TFT15_StarGuardian",
            "num_units": 1,
            "style": 0,
            "tier_current": 0,
            "tier_total": 12
          },
          {
            "name": "TFT15_SupremeCells",
            "num_units": 1,
            "style": 0,
            "tier_current": 0,
            "tier_total": 3
          },
          {
            "name": "TFT15_TheCrew",
            "num_units": 2,
            "style": 1,
            "tier_current": 7,
            "tier_total": 7
          }
        ],
        "units": [
          {
            "character_id": "TFT15_Kennen",
            "itemNames": [
              "TFT15_Item_SniperEmblemItem",
              "TFT_Item_SpectralGauntlet"
            ],
            "name": "",
            "rarity": 0,
            "tier": 3
          },
          {
            "character_id": "TFT15_Gnar",
            "itemNames": [],
            "name": "",
            "rarity": 0,
            "tier": 2
          },
          {
            "character_id": "TFT15_Sivir",
            "itemNames": [
              "TFT_Item_GuardianAngel",
              "TFT_Item_SpearOfShojin"
            ],
            "name": "",
            "rarity": 0,
            "tier": 3
          },
          {
            "character_id": "TFT15_Malphite",
            "itemNames": [
              "TFT_Item_Redemption",
              "TFT_Item_GargoyleStoneplate",
              "TFT_Item_GargoyleStoneplate"
            ],
            "name": "",
            "rarity": 0,
            "tier": 3
          },
          {
            "character_id": "TFT15_Rakan",
            "itemNames": [
              "TFT_Item_TacticiansRing"
            ],
            "name": "",
            "rarity": 1,
            "tier": 2
          },
          {
            "character_id": "TFT15_Jhin",
            "itemNames": [
              "TFT_Item_InfinityEdge",
              "TFT_Item_MadredsBloodrazor",
              "TFT_Item_GuinsoosRageblade"
            ],
            "name": "",
            "rarity": 1,
            "tier": 3
          },
          {
            "character_id": "TFT15_Neeko",
            "itemNames": [],
            "name": "",
            "rarity": 2,
            "tier": 2
          },
          {
            "character_id": "TFT15_KSante",
            "itemNames": [],
            "name": "",
            "rarity": 4,
            "tier": 1
          }
        ],
        "win": false
      }
    ],
    "queueId": 1100,
    "queue_id": 1100,
    "tft_game_type": "standard",
    "tft_set_core_name": "TFTSet15",
    "tft_set_number": 15
  },
  "collection_info": {
    "start_timestamp": 133660800,
    "collection_timestamp": 1757484492
  }
}